heatshrinkpy/__init__.py
heatshrinkpy/__main__.py
heatshrinkpy/core/__init__.py
heatshrinkpy/core/common.py
heatshrinkpy/core/consts.py
heatshrinkpy/core/decoder.py
heatshrinkpy/core/encoder.py
heatshrinkpy/streams.py
heatshrinkpy/version.py
heatshrinkpy-0.11.1.dist-info/LICENSE
heatshrinkpy-0.11.1.dist-info/METADATA
heatshrinkpy-0.11.1.dist-info/WHEEL
heatshrinkpy-0.11.1.dist-info/entry_points.txt
heatshrinkpy-0.11.1.dist-info/RECORD
