Metadata-Version: 2.1
Name: heatshrinkpy
Version: 0.11.1
Summary: Pure Python heatshrink library, based on heatshrink2 library
License: ISC
Author: Marcin Jaworski
Author-email: marcin@jaworski.me
Requires-Python: >=3.7,<4.0
Classifier: License :: OSI Approved
Classifier: Programming Language :: Python :: 3
Classifier: Programming Language :: Python :: 3.7
Classifier: Programming Language :: Python :: 3.8
Classifier: Programming Language :: Python :: 3.9
Classifier: Programming Language :: Python :: 3.10
Classifier: Programming Language :: Python :: 3.11
Requires-Dist: importlib-metadata (>=6.6.0,<7.0.0) ; python_version < "3.8"
